{
  "main": {
    "id": "b7209059617937d6",
    "type": "split",
    "children": [
      {
        "id": "7da235c3362cfbec",
        "type": "tabs",
        "children": [
          {
            "id": "f4ac642c8a8c1561",
            "type": "leaf",
            "pinned": true,
            "state": {
              "type": "markdown",
              "state": {
                "file": "Organisation/How To Use.md",
                "mode": "source",
                "source": false,
                "backlinks": true,
                "backlinkOpts": {
                  "collapseAll": false,
                  "extraContext": false,
                  "sortOrder": "alphabetical",
                  "showSearch": false,
                  "searchQuery": "",
                  "backlinkCollapsed": false,
                  "unlinkedCollapsed": true
                }
              },
              "pinned": true,
              "icon": "lucide-file",
              "title": "How To Use"
            }
          },
          {
            "id": "92f16509498306cb",
            "type": "leaf",
            "state": {
              "type": "markdown",
              "state": {
                "file": "Submission/Walls of Jericho.md",
                "mode": "source",
                "source": false,
                "backlinks": true,
                "backlinkOpts": {
                  "collapseAll": false,
                  "extraContext": false,
                  "sortOrder": "alphabetical",
                  "showSearch": false,
                  "searchQuery": "",
                  "backlinkCollapsed": false,
                  "unlinkedCollapsed": true
                }
              },
              "icon": "lucide-file",
              "title": "Walls of Jericho"
            },
            "group": "f018b5ed72bc1c7c"
          }
        ],
        "currentTab": 1
      },
      {
        "id": "3790013d5f8c6be7",
        "type": "split",
        "children": [
          {
            "id": "1bb309d5787bee7b",
            "type": "tabs",
            "dimension": 57.11610486891385,
            "children": [
              {
                "id": "d56eaae85eca83d8",
                "type": "leaf",
                "state": {
                  "type": "localgraph",
                  "state": {
                    "file": "Submission/Walls of Jericho.md",
                    "options": {
                      "collapse-filter": true,
                      "search": "",
                      "localJumps": 1,
                      "localBacklinks": false,
                      "localForelinks": true,
                      "localInterlinks": false,
                      "showTags": false,
                      "showAttachments": false,
                      "hideUnresolved": true,
                      "collapse-color-groups": true,
                      "colorGroups": [
                        {
                          "query": "path:Position  ",
                          "color": {
                            "a": 1,
                            "rgb": 331248
                          }
                        },
                        {
                          "query": "path:Submission  ",
                          "color": {
                            "a": 1,
                            "rgb": 5431380
                          }
                        }
                      ],
                      "collapse-display": true,
                      "showArrow": true,
                      "textFadeMultiplier": 0,
                      "nodeSizeMultiplier": 1,
                      "lineSizeMultiplier": 1,
                      "collapse-forces": true,
                      "centerStrength": 0.518713248970312,
                      "repelStrength": 10,
                      "linkStrength": 1,
                      "linkDistance": 250,
                      "scale": 1,
                      "close": true
                    }
                  },
                  "icon": "lucide-git-fork",
                  "title": "Graph of Walls of Jericho"
                },
                "group": "f018b5ed72bc1c7c"
              }
            ]
          },
          {
            "id": "6691803bdbb7b201",
            "type": "tabs",
            "dimension": 42.88389513108614,
            "children": [
              {
                "id": "bd550bc808a4b1e6",
                "type": "leaf",
                "state": {
                  "type": "backlink",
                  "state": {
                    "file": "Submission/Walls of Jericho.md",
                    "collapseAll": false,
                    "extraContext": false,
                    "sortOrder": "alphabetical",
                    "showSearch": false,
                    "searchQuery": "",
                    "backlinkCollapsed": false,
                    "unlinkedCollapsed": true
                  },
                  "icon": "links-coming-in",
                  "title": "Backlinks for Walls of Jericho"
                },
                "group": "f018b5ed72bc1c7c"
              },
              {
                "id": "7fd73c22ce824d2e",
                "type": "leaf",
                "state": {
                  "type": "outgoing-link",
                  "state": {
                    "file": "Submission/Walls of Jericho.md",
                    "linksCollapsed": false,
                    "unlinkedCollapsed": true
                  },
                  "icon": "links-going-out",
                  "title": "Outgoing links from Walls of Jericho"
                },
                "group": "f018b5ed72bc1c7c"
              }
            ],
            "currentTab": 1
          }
        ],
        "direction": "horizontal"
      }
    ],
    "direction": "vertical"
  },
  "left": {
    "id": "6d4de21d8f91c80b",
    "type": "split",
    "children": [
      {
        "id": "e8cf8ab0f645c7ed",
        "type": "tabs",
        "children": [
          {
            "id": "af03b14e31fc5d02",
            "type": "leaf",
            "state": {
              "type": "file-explorer",
              "state": {
                "sortOrder": "alphabetical",
                "autoReveal": false
              },
              "icon": "lucide-folder-closed",
              "title": "Files"
            }
          },
          {
            "id": "5de4580475faeea1",
            "type": "leaf",
            "state": {
              "type": "search",
              "state": {
                "query": "",
                "matchingCase": false,
                "explainSearch": false,
                "collapseAll": false,
                "extraContext": false,
                "sortOrder": "alphabetical"
              },
              "icon": "lucide-search",
              "title": "Search"
            }
          },
          {
            "id": "a74883873a7d74f2",
            "type": "leaf",
            "state": {
              "type": "bookmarks",
              "state": {},
              "icon": "lucide-bookmark",
              "title": "Bookmarks"
            }
          }
        ]
      }
    ],
    "direction": "horizontal",
    "width": 246.50775146484375
  },
  "right": {
    "id": "e49dd5869bf2716e",
    "type": "split",
    "children": [
      {
        "id": "ab285b1a0dc21d58",
        "type": "tabs",
        "children": [
          {
            "id": "8428fecd27ed3071",
            "type": "leaf",
            "pinned": true,
            "state": {
              "type": "graph",
              "state": {},
              "pinned": true,
              "icon": "lucide-git-fork",
              "title": "Graph view"
            }
          },
          {
            "id": "a04e63657f10bd3c",
            "type": "leaf",
            "state": {
              "type": "backlink",
              "state": {
                "collapseAll": false,
                "extraContext": false,
                "sortOrder": "alphabetical",
                "showSearch": false,
                "searchQuery": "",
                "backlinkCollapsed": false,
                "unlinkedCollapsed": true
              },
              "icon": "links-coming-in",
              "title": "Backlinks"
            }
          },
          {
            "id": "c680ba53b5a3673f",
            "type": "leaf",
            "state": {
              "type": "outgoing-link",
              "state": {
                "linksCollapsed": false,
                "unlinkedCollapsed": true
              },
              "icon": "links-going-out",
              "title": "Outgoing links"
            }
          },
          {
            "id": "d47a6a801232b675",
            "type": "leaf",
            "state": {
              "type": "tag",
              "state": {
                "sortOrder": "frequency",
                "useHierarchy": true,
                "showSearch": false,
                "searchQuery": ""
              },
              "icon": "lucide-tags",
              "title": "Tags"
            }
          },
          {
            "id": "b2f6f8af55972144",
            "type": "leaf",
            "state": {
              "type": "all-properties",
              "state": {
                "sortOrder": "frequency",
                "showSearch": false,
                "searchQuery": ""
              },
              "icon": "lucide-archive",
              "title": "All properties"
            }
          },
          {
            "id": "258478c0ed3de121",
            "type": "leaf",
            "state": {
              "type": "outline",
              "state": {
                "followCursor": false,
                "showSearch": false,
                "searchQuery": ""
              },
              "icon": "lucide-list",
              "title": "Outline"
            }
          }
        ]
      }
    ],
    "direction": "horizontal",
    "width": 593.5
  },
  "left-ribbon": {
    "hiddenItems": {
      "graph:Open graph view": false,
      "switcher:Open quick switcher": false,
      "canvas:Create new canvas": false,
      "daily-notes:Open today's daily note": false,
      "templates:Insert template": false,
      "command-palette:Open command palette": false,
      "bases:Create new base": false
    }
  },
  "active": "92f16509498306cb",
  "lastOpenFiles": [
    "Submission/Wicked Gogoplata.md",
    "Submission/Walls of Jericho.md",
    "Submission/Von Flue Choke.md",
    "Submission/Twister.md",
    "Submission/Triangle.md",
    "Submission/Toe Hold.md",
    "Submission/The Oprah.md",
    "Submission/Tepee Choke.md",
    "Submission/Tickle.md",
    "Submission/The Shark.md",
    "Submission/Hip Choke.md",
    "Submission/Banana Split.md",
    "Submission/Canto Choke.md",
    "Submission/Badger Bite.md",
    "Submission/Aoki Lock.md",
    "Submission/STF.md",
    "Submission/Animal Planet.md",
    "Jesus Curls.md",
    "Submission/Diesel Squeezel.md",
    "Submission/Tepee Crush.md",
    "Submission/Butcher Shop.md",
    "Submission/Bulldog Choke (reverse).md",
    "Submission/The Hoover.md",
    "Submission/Triangle Punch Choke.md",
    "Submission/Tren Lock.md",
    "Submission/Mikey Lock.md",
    "Organisation/Attachments/Pasted image 20260201233612.png",
    "Organisation/Attachments/Pasted image 20260201233141.png",
    "Organisation/Attachments/Pasted image 20260201232827.png",
    "Organisation/Attachments/Pasted image 20260201230855.png",
    "Organisation/Attachments/Pasted image 20260201230552.png",
    "Organisation/Attachments/Pasted image 20260201230155.png",
    "Organisation/Attachments/Pasted image 20260201225949.png",
    "Organisation/Attachments/Pasted image 20260201225802.png",
    "Organisation/Attachments/Pasted image 20260201224353.png",
    "Organisation/Attachments/Pasted image 20260202230024.png",
    "Organisation/Index.base",
    "Organisation/Attachments",
    "90",
    "70",
    "50",
    "Untitled 1.canvas",
    "Untitled.canvas",
    "Organisation/Resources/Video Series",
    "Organisation/Resources/Clips",
    "Organisation/Resources/Books",
    "Organisation/Resources",
    "Organisation/Templates"
  ]
}